<?xml version="1.0" encoding="UTF-8"?>
<!DOCTYPE catmetadata SYSTEM "http://www.gentoo.org/dtd/metadata.dtd">
<catmetadata>
	<longdescription lang="en">
		The app-accessibility category contains packages which help with
		accessibility (for example, screen readers).
	</longdescription>
	<longdescription lang="es">
		La categoría app-accessibility contiene paquetes para ayudar con 
		accesibilidad (por ejemplo, lectores de pantallas).
	</longdescription>
	<longdescription lang="de">
		Die Kategorie app-accessibility enthält Programme für barrierefreies
		Arbeiten (Accessibility), wie beispielsweise Screenreader.
	</longdescription>
	<longdescription lang="nl">
		De app-accessibility categorie bevat applicaties die de
		toegankelijkheid bevorderen, bijvoorbeeld een schermlezer.
	</longdescription>
	<longdescription lang="ja">
		app-accessibilityカテゴリィにはアクセシビリティと
		手伝うパッケージが含まれます。
	</longdescription>
	<longdescription lang="vi">
		Nhóm app-accessibility chứa các gói trợ giúp về truy nhập (ví dụ, trình đọc màn hình)
	</longdescription>
</catmetadata>

